amphi/_version.py
jupyterlab_amphi-0.9.2.data/data/share/jupyter/labextensions/@amphi/_version.py
jupyterlab_amphi-0.9.2.data/data/share/jupyter/labextensions/@amphi/pipeline-components-core/package.json
jupyterlab_amphi-0.9.2.data/data/share/jupyter/labextensions/@amphi/pipeline-components-core/static/432.004e3a9ca1397bf3d8fd.js
jupyterlab_amphi-0.9.2.data/data/share/jupyter/labextensions/@amphi/pipeline-components-core/static/447.55ce7a6d17f29f9c5a17.js
jupyterlab_amphi-0.9.2.data/data/share/jupyter/labextensions/@amphi/pipeline-components-core/static/447.55ce7a6d17f29f9c5a17.js.LICENSE.txt
jupyterlab_amphi-0.9.2.data/data/share/jupyter/labextensions/@amphi/pipeline-components-core/static/480.69d83bc8bf58305edbea.js
jupyterlab_amphi-0.9.2.data/data/share/jupyter/labextensions/@amphi/pipeline-components-core/static/480.69d83bc8bf58305edbea.js.LICENSE.txt
jupyterlab_amphi-0.9.2.data/data/share/jupyter/labextensions/@amphi/pipeline-components-core/static/54.a30a3f14b3f9f57b0a18.js
jupyterlab_amphi-0.9.2.data/data/share/jupyter/labextensions/@amphi/pipeline-components-core/static/554.ad6261c63b366a4d36d7.js
jupyterlab_amphi-0.9.2.data/data/share/jupyter/labextensions/@amphi/pipeline-components-core/static/554.ad6261c63b366a4d36d7.js.LICENSE.txt
jupyterlab_amphi-0.9.2.data/data/share/jupyter/labextensions/@amphi/pipeline-components-core/static/624.0b7064cd96625b928cc5.js
jupyterlab_amphi-0.9.2.data/data/share/jupyter/labextensions/@amphi/pipeline-components-core/static/624.0b7064cd96625b928cc5.js.LICENSE.txt
jupyterlab_amphi-0.9.2.data/data/share/jupyter/labextensions/@amphi/pipeline-components-core/static/remoteEntry.06ee7fe6ea686177ec91.js
jupyterlab_amphi-0.9.2.data/data/share/jupyter/labextensions/@amphi/pipeline-components-core/static/style.js
jupyterlab_amphi-0.9.2.data/data/share/jupyter/labextensions/@amphi/pipeline-components-core/static/third-party-licenses.json
jupyterlab_amphi-0.9.2.dist-info/METADATA
jupyterlab_amphi-0.9.2.dist-info/WHEEL
jupyterlab_amphi-0.9.2.dist-info/licenses/LICENSE
jupyterlab_amphi-0.9.2.dist-info/RECORD
