Metadata-Version: 2.4
Name: jupyterlab-amphi
Version: 0.9.2
Dynamic: Keywords
Summary: Amphi is a no-code ETL extension for Jupyterlab.
Project-URL: Homepage, https://amphi.ai
Project-URL: Bug Tracker, https://github.com/amphi-ai/jupyterlab-amphi/issues
Project-URL: Repository, https://github.com/amphi-ai/jupyterlab-amphi.git
Author-email: Thibaut Gourdel <tgourdel@amphi.ai>
License: Elastic License 2.0 \(ELv2\)
License-File: LICENSE
Classifier: Framework :: Jupyter
Classifier: Framework :: Jupyter :: JupyterLab
Classifier: Framework :: Jupyter :: JupyterLab :: 4
Classifier: Framework :: Jupyter :: JupyterLab :: Extensions
Classifier: Framework :: Jupyter :: JupyterLab :: Extensions :: Prebuilt
Classifier: Programming Language :: Python
Classifier: Programming Language :: Python :: 3
Classifier: Programming Language :: Python :: 3.8
Classifier: Programming Language :: Python :: 3.9
Classifier: Programming Language :: Python :: 3.10
Classifier: Programming Language :: Python :: 3.11
Classifier: Programming Language :: Python :: 3.12
Requires-Python: >=3.8
